bin/duvc-core.dll
bin/__init__.py
duvc_ctl/CameraController.py
duvc_ctl/exceptions.py
duvc_ctl/py.typed
duvc_ctl/_duvc_ctl.cp311-win_amd64.pyd
duvc_ctl/__init__.py
duvc_ctl-2.0.1.dist-info/DELVEWHEEL
duvc_ctl-2.0.1.dist-info/METADATA
duvc_ctl-2.0.1.dist-info/RECORD
duvc_ctl-2.0.1.dist-info/WHEEL
duvc_ctl.libs/duvc-core.dll
duvc_ctl.libs/msvcp140.dll
include/__init__.py
include/duvc-ctl/core.h
include/duvc-ctl/defs.h
include/duvc-ctl/duvc.hpp
include/duvc-ctl/c/api.h
include/duvc-ctl/c/version.h
include/duvc-ctl/core/camera.h
include/duvc-ctl/core/capability.h
include/duvc-ctl/core/device.h
include/duvc-ctl/core/operations.h
include/duvc-ctl/core/result.h
include/duvc-ctl/core/types.h
include/duvc-ctl/detail/com_helpers.h
include/duvc-ctl/detail/directshow_impl.h
include/duvc-ctl/detail/windows_internal.h
include/duvc-ctl/legacy/core.h
include/duvc-ctl/legacy/defs.h
include/duvc-ctl/platform/interface.h
include/duvc-ctl/platform/windows/connection_pool.h
include/duvc-ctl/platform/windows/directshow.h
include/duvc-ctl/platform/windows/ks_properties.h
include/duvc-ctl/utils/error_decoder.h
include/duvc-ctl/utils/logging.h
include/duvc-ctl/utils/string_conversion.h
include/duvc-ctl/vendor/constants.h
include/duvc-ctl/vendor/logitech.h
lib/duvc-core.lib
lib/__init__.py
lib/cmake/duvc-ctl/duvc-config-version.cmake
lib/cmake/duvc-ctl/duvc-config.cmake
lib/cmake/duvc-ctl/duvc-targets-release.cmake
lib/cmake/duvc-ctl/duvc-targets.cmake
lib/pkgconfig/duvc.pc
