Metadata-Version: 2.1
Name: duvc-ctl
Version: 2.0.1
Summary: DirectShow UVC Camera Control Library
Keywords: camera,uvc,directshow,ptz,video,control,webcam
Author-Email: allanhanan <allan.hanan04@gmail.com>
License: MIT License
Classifier: Development Status :: 5 - Production/Stable
Classifier: Intended Audience :: Developers
Classifier: License :: OSI Approved :: MIT License
Classifier: Operating System :: Microsoft :: Windows
Classifier: Programming Language :: Python :: 3
Classifier: Programming Language :: Python :: 3.8
Classifier: Programming Language :: Python :: 3.9
Classifier: Programming Language :: Python :: 3.10
Classifier: Programming Language :: Python :: 3.11
Classifier: Programming Language :: Python :: 3.12
Classifier: Programming Language :: C++
Classifier: Topic :: Multimedia :: Video
Classifier: Topic :: Software Development :: Libraries :: Python Modules
Classifier: Topic :: System :: Hardware :: Hardware Drivers
Project-URL: Homepage, https://github.com/allanhanan/duvc-ctl
Project-URL: Repository, https://github.com/allanhanan/duvc-ctl
Project-URL: Documentation, https://github.com/allanhanan/duvc-ctl/blob/main/README.md
Project-URL: Bug Reports, https://github.com/allanhanan/duvc-ctl/issues
Requires-Python: >=3.8
Provides-Extra: dev
Requires-Dist: pytest>=6.0; extra == "dev"
Requires-Dist: pytest-cov; extra == "dev"
Requires-Dist: black; extra == "dev"
Requires-Dist: isort; extra == "dev"
Requires-Dist: mypy; extra == "dev"
Requires-Dist: build; extra == "dev"
Requires-Dist: twine; extra == "dev"
